{"stat.drop.minecraft.potion":1,"stat.pickup.minecraft.rotten_flesh":1,"stat.killEntity.Skeleton":5,"stat.walkOneCm":6099,"stat.pickup.minecraft.bone":3,"stat.killEntity.Horse":3,"stat.pickup.minecraft.potion":1,"stat.leaveGame":1,"stat.killEntity.Slime":7,"stat.killEntity.Spider":2,"stat.damageTaken":200,"stat.pickup.minecraft.leather":1,"stat.drop.minecraft.ender_pearl":1,"stat.mobKills":25,"stat.killEntity.Creeper":1,"stat.useItem.minecraft.diamond_sword":40,"stat.useItem.minecraft.potion":5,"stat.flyOneCm":33879,"stat.useItem.minecraft.ender_pearl":11,"stat.deaths":1,"stat.drop.minecraft.bedrock":10,"stat.drop":12,"stat.jump":140,"stat.swimOneCm":77,"stat.playOneMinute":4851,"stat.killEntity.Sheep":2,"stat.sneakTime":2,"stat.killEntity.Villager":1,"stat.damageDealt":3829,"stat.pickup.minecraft.gunpowder":2,"stat.pickup.minecraft.porkchop":3,"stat.killEntity.Zombie":3,"stat.timeSinceDeath":2483,"stat.sprintOneCm":12960,"stat.killEntity.Pig":1,"stat.diveOneCm":9225}